sd_notify.py
sd_notify-0.1.0.dist-info/LICENSE
sd_notify-0.1.0.dist-info/METADATA
sd_notify-0.1.0.dist-info/WHEEL
sd_notify-0.1.0.dist-info/top_level.txt
sd_notify-0.1.0.dist-info/RECORD
