Metadata-Version: 2.1
Name: sd-notify
Version: 0.1.0
Summary: Simple sd_notify client library for Python 3
Home-page: http://github.com/stigok/sd-notify/
Author: stigok
Author-email: stig@stigok.com
License: UNKNOWN
Project-URL: Bug Tracker, http://github.com/stigok/sd-notify/issues
Project-URL: Documentation, http://github.com/stigok/sd-notify/
Project-URL: Source Code, http://github.com/stigok/sd-notify/
Keywords: sd-notify systemd python3 watchdog
Platform: UNKNOWN
Classifier: License :: OSI Approved :: MIT License
Classifier: Programming Language :: Python :: 3 :: Only
Requires-Python: >=3.5
